README.md
pyproject.toml
setup.py
agentbee/__init__.py
agentbee/config.py
agentbee/contexts.py
agentbee/logger.py
agentbee/main.py
agentbee.egg-info/PKG-INFO
agentbee.egg-info/SOURCES.txt
agentbee.egg-info/dependency_links.txt
agentbee.egg-info/entry_points.txt
agentbee.egg-info/requires.txt
agentbee.egg-info/top_level.txt
agentbee/core/__init__.py
agentbee/core/accumulator.py
agentbee/core/file_io.py
agentbee/core/llm_api.py
agentbee/core/runner.py