Metadata-Version: 2.1
Name: agentbee
Version: 0.0.2
Summary: An AI-powered code assistant to analyze, assist with, and automate code modifications.
Home-page: https://github.com/buildybee/agentbee
Author: buildybee
Author-email: paul.sayan@gmail.com
Requires-Python: >=3.8
Requires-Dist: typer[all]
Requires-Dist: openai
Requires-Dist: python-dotenv
